responsecodes/__init__.py
responsecodes/__version__.py
responsecodes/responsecodes.py
responsecodes-0.0.1.dist-info/LICENSE
responsecodes-0.0.1.dist-info/METADATA
responsecodes-0.0.1.dist-info/WHEEL
responsecodes-0.0.1.dist-info/top_level.txt
responsecodes-0.0.1.dist-info/RECORD
